terminal_temple/__init__.py
terminal_temple/pizzazz.py
terminal_temple/puzzles.py
terminal_temple/terminal_temple.py
terminal_temple/data/animuls.fasta
terminal_temple/data/greeting.txt
terminal_temple/data/head.png
terminal_temple/data/linux.txt
terminal_temple/data/locations.txt
terminal_temple/data/mlk.txt
terminal_temple/data/moai.txt
terminal_temple/data/reaper.txt
terminal_temple/data/script.txt
terminal_temple-0.1.5.dist-info/DESCRIPTION.rst
terminal_temple-0.1.5.dist-info/METADATA
terminal_temple-0.1.5.dist-info/RECORD
terminal_temple-0.1.5.dist-info/WHEEL
terminal_temple-0.1.5.dist-info/entry_points.txt
terminal_temple-0.1.5.dist-info/metadata.json
terminal_temple-0.1.5.dist-info/top_level.txt
